bs4-stubs/METADATA.toml
bs4-stubs/__init__.pyi
bs4-stubs/dammit.pyi
bs4-stubs/diagnose.pyi
bs4-stubs/element.pyi
bs4-stubs/formatter.pyi
bs4-stubs/py.typed
bs4-stubs/builder/__init__.pyi
bs4-stubs/builder/_html5lib.pyi
bs4-stubs/builder/_htmlparser.pyi
bs4-stubs/builder/_lxml.pyi
types_beautifulsoup4-4.12.0.20241020.dist-info/METADATA
types_beautifulsoup4-4.12.0.20241020.dist-info/WHEEL
types_beautifulsoup4-4.12.0.20241020.dist-info/top_level.txt
types_beautifulsoup4-4.12.0.20241020.dist-info/RECORD
